trame_launcher_nomad/__init__.py
trame_launcher_nomad/server/__init__.py
trame_launcher_nomad/server/main.py
trame_launcher_nomad/www/__init__.py
trame_launcher_nomad/www/index.html
trame_launcher_nomad/www/__pycache__/__init__.cpython-39.pyc
trame_launcher_nomad-0.0.1.dist-info/LICENSE
trame_launcher_nomad-0.0.1.dist-info/METADATA
trame_launcher_nomad-0.0.1.dist-info/WHEEL
trame_launcher_nomad-0.0.1.dist-info/entry_points.txt
trame_launcher_nomad-0.0.1.dist-info/top_level.txt
trame_launcher_nomad-0.0.1.dist-info/RECORD
