Metadata-Version: 2.1
Name: trame-launcher-nomad
Version: 0.0.1
Summary: Launcher for Trame application onto a Nomad managed cluster
Home-page: UNKNOWN
Author: Kitware Inc.
License: BSD License
Keywords: Python,Interactive,Web,Application,Framework
Platform: UNKNOWN
Classifier: Development Status :: 1 - Planning
Classifier: Environment :: Web Environment
Classifier: License :: OSI Approved :: BSD License
Classifier: Natural Language :: English
Classifier: Operating System :: OS Independent
Classifier: Programming Language :: Python :: 3 :: Only
Classifier: Programming Language :: JavaScript
Classifier: Topic :: Software Development :: Libraries :: Application Frameworks
Classifier: Topic :: Software Development :: Libraries :: Python Modules
License-File: LICENSE
Requires-Dist: aiohttp
Requires-Dist: python-nomad
